Metadata-Version: 1.1
Name: kupfer-plugin-empathetic
Version: 0.1.0
Summary: Access to Empathy Contacts
Home-page: https://github.com/hugosenari/empathetic
Author: Jakh Daven
Author-email: tuxcanfly@gmail.com
License: GNU General Public License v3
Keywords: kupfer empathetic
Platform: UNKNOWN
Classifier: Development Status :: 2 - Pre-Alpha
Classifier: Intended Audience :: Developers
Classifier: License :: OSI Approved :: GNU General Public License v3 (GPLv3)
Classifier: Natural Language :: English
Classifier: Programming Language :: Python :: 2
Classifier: Programming Language :: Python :: 2.7
Classifier: Programming Language :: Python :: 3
Classifier: Programming Language :: Python :: 3.3
Classifier: Programming Language :: Python :: 3.4
Classifier: Programming Language :: Python :: 3.5
